harold/__init__.py
harold/_arg_utils.py
harold/_array_validators.py
harold/_aux_linalg.py
harold/_bd_algebra.py
harold/_classes.py
harold/_discrete_funcs.py
harold/_frequency_domain.py
harold/_frequency_domain_plots.py
harold/_global_constants.py
harold/_kalman_ops.py
harold/_polynomial_ops.py
harold/_solvers.py
harold/_static_ctrl_design.py
harold/_system_funcs.py
harold/_system_props.py
harold/_time_domain.py
harold/_time_domain_plots.py
harold/_version.py
harold/tests/test_array_validators.py
harold/tests/test_aux_linalg.py
harold/tests/test_bd_algebra.py
harold/tests/test_classes.py
harold/tests/test_discretize.py
harold/tests/test_frequency_domain.py
harold/tests/test_frequency_domain_plots.py
harold/tests/test_kalman_ops.py
harold/tests/test_polynomial_ops.py
harold/tests/test_solvers.py
harold/tests/test_static_ctrl_design.py
harold/tests/test_system_funcs.py
harold/tests/test_system_props.py
harold/tests/test_time_domain.py
harold/tests/test_time_domain_plots.py
harold-1.0.3.dist-info/LICENSE
harold-1.0.3.dist-info/WHEEL
harold-1.0.3.dist-info/METADATA
harold-1.0.3.dist-info/RECORD
