Metadata-Version: 2.1
Name: harold
Version: 1.0.3
Summary: An open-source systems and controls toolbox for Python3.
License: MIT
Author: Ilhan Polat
Author-email: ilhanpolat@gmail.com
Requires-Python: >=3.8,<4.0
Classifier: Development Status :: 5 - Production/Stable
Classifier: Intended Audience :: Developers
Classifier: Intended Audience :: Science/Research
Classifier: License :: OSI Approved :: MIT License
Classifier: Programming Language :: Python
Classifier: Programming Language :: Python :: 3
Classifier: Programming Language :: Python :: 3.8
Classifier: Programming Language :: Python :: 3.9
Classifier: Programming Language :: Python :: 3.10
Classifier: Programming Language :: Python :: 3.11
Classifier: Programming Language :: Python :: 3
Classifier: Programming Language :: Python :: 3.10
Classifier: Programming Language :: Python :: 3.8
Classifier: Programming Language :: Python :: 3.9
Classifier: Topic :: Scientific/Engineering
Classifier: Topic :: Software Development
Classifier: Topic :: Software Development :: Build Tools
Requires-Dist: matplotlib (>=3.4.0,<4.0.0)
Requires-Dist: scipy (>=1.8.0,<2.0.0)
Requires-Dist: tabulate (>=0.8.9,<0.9.0)
